docs/__init__.py
docs/conf.py
hagent/__init__.py
hagent/module.py
tests/__init__.py
tests/test_example.py
hagent-0.0.1.dist-info/LICENSE.txt
hagent-0.0.1.dist-info/METADATA
hagent-0.0.1.dist-info/WHEEL
hagent-0.0.1.dist-info/top_level.txt
hagent-0.0.1.dist-info/RECORD
