Metadata-Version: 2.1
Name: hagent
Version: 0.0.1
Summary: hagent framework library
Home-page: https://github.com/jbheeman/hagent
Author: Jesh
License-File: LICENSE.txt
